{
  "gitSyncId": "681b61211413e43ed3535f6d_5a7770f5-d622-44d5-9e0f-6c83c12e7742",
  "id": "BossPage_JSObject1.formatTimestamp",
  "pluginId": "js-plugin",
  "pluginType": "JS",
  "unpublishedAction": {
    "actionConfiguration": {
      "encodeParamsToggle": true,
      "jsArguments": [
        {
          "name": "timestamp"
        }
      ],
      "paginationType": "NONE",
      "timeoutInMillisecond": 10000
    },
    "collectionId": "BossPage_JSObject1",
    "confirmBeforeExecute": false,
    "datasource": {
      "isAutoGenerated": false,
      "name": "UNUSED_DATASOURCE",
      "pluginId": "js-plugin"
    },
    "dynamicBindingPathList": [
      {
        "key": "body"
      }
    ],
    "executeOnLoad": false,
    "fullyQualifiedName": "JSObject1.formatTimestamp",
    "name": "formatTimestamp",
    "pageId": "BossPage",
    "userSetOnLoad": false
  }
}