{
  "gitSyncId": "682204b3042562639da02587_0ddbe486-3deb-4e75-9c22-26e2e9df152a",
  "id": "接受面板_Parser.parseTaskLines",
  "pluginId": "js-plugin",
  "pluginType": "JS",
  "unpublishedAction": {
    "actionConfiguration": {
      "encodeParamsToggle": true,
      "jsArguments": [],
      "paginationType": "NONE",
      "timeoutInMillisecond": 10000
    },
    "collectionId": "接受面板_Parser",
    "confirmBeforeExecute": false,
    "datasource": {
      "isAutoGenerated": false,
      "name": "UNUSED_DATASOURCE",
      "pluginId": "js-plugin"
    },
    "dynamicBindingPathList": [
      {
        "key": "body"
      }
    ],
    "executeOnLoad": false,
    "fullyQualifiedName": "Parser.parseTaskLines",
    "name": "parseTaskLines",
    "pageId": "接受面板",
    "userSetOnLoad": false
  }
}